{
  "3": "Phoenix",
  "4": "Maya",
  "5": "Mia",
  "6": "Mia",
  "7": "Judge",
  "8": "Edgeworth",
  "9": "Payne",
  "10": "Gumshoe",
  "11": "Phone",
  "12": "Public",
  "13": "Bailiff",
  "14": "von Karma",
  "15": "von Karma",
  "16": "Wellington",
  "17": "Byrde",
  "18": "Byrde",
  "19": "Ini",
  "20": "Pearl",
  "21": "Morgan",
  "22": "Hotti",
  "23": "Grey",
  "24": "Lotta",
  "25": "Mia",
  "26": "Nurse",
  "27": "Mimi",
  "28": "Regina",
  "29": "Max",
  "30": "Ben",
  "31": "Moe",
  "32": "Acro",
  "33": "Trilo",
  "34": "Money",
  "35": "Engarde",
  "36": "Andrews",
  "37": "de Killer",
  "38": "de Killer",
  "39": "Oldbag",
  "40": "Powers",
  "41": "TV",
  "45": "Celeste",
  "46": "Russell",
  "47": "Bellboy",
  "48": "PA Notice",
  "49": "Ray Gun",
  "50": "Chief",
  "51": "Detective",
  "52": "Guard",
  "53": "Shoe",
  "54": "Doe"
}
